controller/controller.v
`timescale 1ns/1ps 


module controller(clk,lda,sfta,clra,ldq,sftq,clrq,clrff,decr,ldcnt,addsub,ldm,start,qm1,q0,eqz,done);

output reg lda,sfta,clra,ldq,sftq,clrq,clrff,addsub,ldm,decr,ldcnt,done;
input qm1,q0,eqz,clk,start;

reg [2:0] state ;
parameter s0=3'b000 , s1=3'b001 , s2=3'b010 , s3=3'b011 , s4=3'b100 , s5=3'b101, s6=3'b110;


always@(posedge clk)

begin
case(state)
 
 s0 : if(start) state<=s1;
 
 s1 : state <= s2;
 
 s2 : if ({q0,qm1}==2'b01) state<=s3; 
  else if({q0,qm1}==2'b10) state<=s4;
  else state<=s5;

 s3 : state<=s5;
 
 s4 : state<=s5;
 
 s5 : if({q0,qm1}==2'b01 && !eqz) state <= s3;
 else if({q0,qm1}==2'b10 && !eqz) state<=s4;
 else if(eqz) state<=s6;
 else state<=s5;

 s6 : state<=s6;

 default : state<=s0;
endcase

end

always@(*)

begin
case(state)
 
 s0 : begin clra=0; clrq=0; clrff=0; done=0; lda=0; ldq=0; sfta=0; sftq=0;addsub=0; ldm=0; decr=0; ldcnt=0; end

 s1 : begin ldm=1; clrff=1; clra=1; ldcnt=1; end

 s2 : begin ldq=1; clra=0; clrff=0; ldcnt=0; ldm=0; end
 
 s3 : begin lda=1; addsub=1; ldq=0; sfta=0; sftq=0; decr=0; end
 
 s4 : begin lda=1; addsub=0; end
 
 s5 : begin sfta=1; sftq=1; decr=1; end
 
 s6 : done=1;
 
 default : begin clra=0; sfta=0; ldq=0; sftq=0; end
endcase

end

endmodule

booth/counter.v
`timescale 1ns/1ps

module counter(data_out,dec,ldcr,clk);

output reg [5:0] data_out;
input dec,ldcr,clk; // dec is the decrement signal, ldcr is the load signal, clk is the clock signal


always@(posedge clk)

begin 
  if (ldcr) 
   data_out <= 6'b100000; // load the counter with 32
  else if (dec)
   data_out <= data_out-1;
end

endmodule

booth/pipo.v
`timescale 1ns/1ps

module pipo(data_out,data_in,clk,ldm);

input [31:0] data_in;
input clk,ldm;
output reg [31:0] data_out;


always@(posedge clk)

  if(ldm) data_out <= data_in;

endmodule

booth/dff.v
`timescale 1ns/1ps

module dff(q,d,clk,clrff);

input d,clk,clrff;
output reg q;


 always@(posedge clk)

 begin
   if (clrff)
    q<=0;
   else
    q<=d;
 end
 
 endmodule

booth/alu.v
`timescale 1ns/1ps

module alu(data_out,din1,din2,addsub);

input [31:0] din1,din2;
input addsub;  

output reg [31:0] data_out;


always@(*)

begin
  if(addsub)
   data_out = din1+din2;
  else 
   data_out = din1-din2;
end

endmodule

booth/shiftreg.v
// 32 bit shift register module for A and Q



`timescale 1ns/1ps

module shiftreg(data_out,data_in,s_in,lda,sfta,clra,clk);

input [31:0] data_in;
input clk,lda,sfta,clra,s_in;

output reg [31:0] data_out;


always@(posedge clk)

begin
  if(clra) 
   data_out <= 0;
  else if(lda) // if load signal is high then load the data_in to data_out
   data_out <= data_in;
  else if(sfta) // if shift signal is high then shift 
   data_out <= {s_in,data_out[31:1]} ;
end

endmodule

booth/booth_multiplier.v
`timescale 1ns/1ps

module booth(qm1,eqz,clk,data_in,lda,sfta,clra,ldcnt,sftq,clrq,clrff,ldq,decr,addsub,ldm);

input clk,lda,sfta,clra,ldq,sftq,clrq,clrff,addsub,ldm,decr,ldcnt;
input [31:0] data_in;

output qm1,eqz;

wire [31:0] A,Q,M,Z;
wire [5:0] count;


assign eqz= ~|count;



shiftreg AR(A,Z,A[15],lda,sfta,clra,clk);

shiftreg QR(Q,data_in,A[0],ldq,sftq,clrq,clk);

alu al(Z,A,M,addsub);

dff fq(qm1,Q[0],clk,clrff);

pipo mr(M,data_in,clk,ldm);

counter cr(count,decr,ldcnt,clk);



endmodule

testbench/tb_booth.v
`timescale 1ns/1ps

module tb_booth;

reg [31:0] data_in;
reg clk, start;
wire done;

booth b1 (qm1,eqz,clk,data_in,lda,sfta,clra,ldcnt,sftq,clrq,clrff,ldq,decr,addsub,ldm);
controller con(clk,lda,sfta,clra,ldq,sftq,clrq,clrff,decr,ldcnt,addsub,ldm,start,b1.qm1,b1.Q[0],b1.eqz,done);

initial
begin
    clk = 0;
    #1 start = 1;
    #500 $finish;
end

always #5 clk = ~clk;

initial
begin
    #7 data_in = 172;
    #10 data_in = 15;
end

initial
begin
    $monitor("state=%d, data_in=%d,count=%d, %b,%b, done=%b", con.state, data_in, b1.count,b1.A,b1.Q ,done);
    $dumpfile("tb_booth.vcd"); 
    $dumpvars(0,tb_booth);
end
endmodule

.gitignore/tb_booth.vcd
$date
	Wed Jul 15 00:40:07 2026
$end
$version
	Icarus Verilog
$end
$timescale
	1ps
$end
$scope module tb_booth $end
$var wire 1 ! sftq $end
$var wire 1 " sfta $end
$var wire 1 # qm1 $end
$var wire 1 $ ldq $end
$var wire 1 % ldm $end
$var wire 1 & ldcnt $end
$var wire 1 ' lda $end
$var wire 1 ( eqz $end
$var wire 1 ) done $end
$var wire 1 * decr $end
$var wire 1 + clrq $end
$var wire 1 , clrff $end
$var wire 1 - clra $end
$var wire 1 . addsub $end
$var reg 1 / clk $end
$var reg 32 0 data_in [31:0] $end
$var reg 1 1 start $end
$scope module b1 $end
$var wire 1 / clk $end
$var wire 32 2 data_in [31:0] $end
$var wire 1 ! sftq $end
$var wire 1 " sfta $end
$var wire 1 # qm1 $end
$var wire 1 $ ldq $end
$var wire 1 % ldm $end
$var wire 1 & ldcnt $end
$var wire 1 ' lda $end
$var wire 1 ( eqz $end
$var wire 1 * decr $end
$var wire 6 3 count [5:0] $end
$var wire 1 + clrq $end
$var wire 1 , clrff $end
$var wire 1 - clra $end
$var wire 1 . addsub $end
$var wire 32 4 Z [31:0] $end
$var wire 32 5 Q [31:0] $end
$var wire 32 6 M [31:0] $end
$var wire 32 7 A [31:0] $end
$scope module AR $end
$var wire 1 / clk $end
$var wire 1 8 s_in $end
$var wire 1 " sfta $end
$var wire 1 ' lda $end
$var wire 32 9 data_in [31:0] $end
$var wire 1 - clra $end
$var reg 32 : data_out [31:0] $end
$upscope $end
$scope module QR $end
$var wire 1 / clk $end
$var wire 32 ; data_in [31:0] $end
$var wire 1 < s_in $end
$var wire 1 ! sfta $end
$var wire 1 $ lda $end
$var wire 1 + clra $end
$var reg 32 = data_out [31:0] $end
$upscope $end
$scope module al $end
$var wire 32 > din1 [31:0] $end
$var wire 32 ? din2 [31:0] $end
$var wire 1 . addsub $end
$var reg 32 @ data_out [31:0] $end
$upscope $end
$scope module cr $end
$var wire 1 / clk $end
$var wire 1 & ldcr $end
$var wire 1 * dec $end
$var reg 6 A data_out [5:0] $end
$upscope $end
$scope module fq $end
$var wire 1 / clk $end
$var wire 1 B d $end
$var wire 1 , clrff $end
$var reg 1 # q $end
$upscope $end
$scope module mr $end
$var wire 1 / clk $end
$var wire 32 C data_in [31:0] $end
$var wire 1 % ldm $end
$var reg 32 D data_out [31:0] $end
$upscope $end
$upscope $end
$scope module con $end
$var wire 1 / clk $end
$var wire 1 ( eqz $end
$var wire 1 E q0 $end
$var wire 1 # qm1 $end
$var wire 1 1 start $end
$var parameter 3 F s0 $end
$var parameter 3 G s1 $end
$var parameter 3 H s2 $end
$var parameter 3 I s3 $end
$var parameter 3 J s4 $end
$var parameter 3 K s5 $end
$var parameter 3 L s6 $end
$var reg 1 . addsub $end
$var reg 1 - clra $end
$var reg 1 , clrff $end
$var reg 1 + clrq $end
$var reg 1 * decr $end
$var reg 1 ) done $end
$var reg 1 ' lda $end
$var reg 1 & ldcnt $end
$var reg 1 % ldm $end
$var reg 1 $ ldq $end
$var reg 1 " sfta $end
$var reg 1 ! sftq $end
$var reg 3 M state [2:0] $end
$upscope $end
$upscope $end
$enddefinitions $end
$comment Show the parameter values. $end
$dumpall
b110 L
b101 K
b100 J
b11 I
b10 H
b1 G
b0 F
$end
#0
$dumpvars
bx M
xE
bx D
bx C
xB
bx A
bx @
bx ?
bx >
bx =
x<
bx ;
bx :
bx 9
x8
bx 7
bx 6
bx 5
bx 4
bx 3
bx 2
x1
bx 0
0/
x.
x-
x,
x+
x*
x)
x(
x'
x&
x%
x$
x#
x"
x!
$end
#1000
11
#5000
0&
0*
0%
0.
0!
0"
0$
0'
0)
0,
0+
0-
b0 M
1/
#7000
b10101100 0
b10101100 2
b10101100 ;
b10101100 C
#10000
0/
#15000
1&
1-
1,
1%
b1 M
1/
#17000
b1111 0
b1111 2
b1111 ;
b1111 C
#20000
0/
#25000
0<
08
b11111111111111111111111111110001 4
b11111111111111111111111111110001 9
b11111111111111111111111111110001 @
0%
0&
0,
0-
1$
b0 7
b0 :
b0 >
0#
b1111 6
b1111 ?
b1111 D
0(
b100000 3
b100000 A
b10 M
1/
#30000
0/
#35000
1*
1!
1"
1E
1B
b101 M
x#
b1111 5
b1111 =
1/
#40000
0/
#45000
1#
b11111 3
b11111 A
1/
#50000
0/
#55000
b11110 3
b11110 A
1/
#60000
0/
#65000
b11101 3
b11101 A
1/
#70000
0/
#75000
b11100 3
b11100 A
1/
#80000
0/
#85000
b11011 3
b11011 A
1/
#90000
0/
#95000
b11010 3
b11010 A
1/
#100000
0/
#105000
b11001 3
b11001 A
1/
#110000
0/
#115000
b11000 3
b11000 A
1/
#120000
0/
#125000
b10111 3
b10111 A
1/
#130000
0/
#135000
b10110 3
b10110 A
1/
#140000
0/
#145000
b10101 3
b10101 A
1/
#150000
0/
#155000
b10100 3
b10100 A
1/
#160000
0/
#165000
b10011 3
b10011 A
1/
#170000
0/
#175000
b10010 3
b10010 A
1/
#180000
0/
#185000
b10001 3
b10001 A
1/
#190000
0/
#195000
b10000 3
b10000 A
1/
#200000
0/
#205000
b1111 3
b1111 A
1/
#210000
0/
#215000
b1110 3
b1110 A
1/
#220000
0/
#225000
b1101 3
b1101 A
1/
#230000
0/
#235000
b1100 3
b1100 A
1/
#240000
0/
#245000
b1011 3
b1011 A
1/
#250000
0/
#255000
b1010 3
b1010 A
1/
#260000
0/
#265000
b1001 3
b1001 A
1/
#270000
0/
#275000
b1000 3
b1000 A
1/
#280000
0/
#285000
b111 3
b111 A
1/
#290000
0/
#295000
b110 3
b110 A
1/
#300000
0/
#305000
b101 3
b101 A
1/
#310000
0/
#315000
b100 3
b100 A
1/
#320000
0/
#325000
b11 3
b11 A
1/
#330000
0/
#335000
b10 3
b10 A
1/
#340000
0/
#345000
b1 3
b1 A
1/
#350000
0/
#355000
1(
b0 3
b0 A
1/
#360000
0/
#365000
1)
0(
b111111 3
b111111 A
b110 M
1/
#370000
0/
#375000
b111110 3
b111110 A
1/
#380000
0/
#385000
b111101 3
b111101 A
1/
#390000
0/
#395000
b111100 3
b111100 A
1/
#400000
0/
#405000
b111011 3
b111011 A
1/
#410000
0/
#415000
b111010 3
b111010 A
1/
#420000
0/
#425000
b111001 3
b111001 A
1/
#430000
0/
#435000
b111000 3
b111000 A
1/
#440000
0/
#445000
b110111 3
b110111 A
1/
#450000
0/
#455000
b110110 3
b110110 A
1/
#460000
0/
#465000
b110101 3
b110101 A
1/
#470000
0/
#475000
b110100 3
b110100 A
1/
#480000
0/
#485000
b110011 3
b110011 A
1/
#490000
0/
#495000
b110010 3
b110010 A
1/
